{
  "version": "5",
  "dialect": "sqlite",
  "id": "c16b552a-b47a-487b-bd12-07945fee7b8d",
  "prevId": "6b113708-f340-485d-b3c2-69a4f411bd0a",
  "tables": {
    "cache_keys": {
      "name": "cache_keys",
      "columns": {
        "key": {
          "name": "key",
          "type": "text",
          "primaryKey": false,
          "notNull": true,
          "autoincrement": false
        },
        "version": {
          "name": "version",
          "type": "text",
          "primaryKey": false,
          "notNull": true,
          "autoincrement": false
        },
        "updated_at": {
          "name": "updated_at",
          "type": "text",
          "primaryKey": false,
          "notNull": true,
          "autoincrement": false
        }
      },
      "indexes": {},
      "foreignKeys": {},
      "compositePrimaryKeys": {
        "cache_keys_key_version_pk": {
          "columns": ["key", "version"],
          "name": "cache_keys_key_version_pk"
        }
      },
      "uniqueConstraints": {}
    }
  },
  "enums": {},
  "_meta": {
    "schemas": {},
    "tables": {},
    "columns": {}
  }
}
